dash_arcgis/__init__.py
dash_arcgis-0.0.1.dist-info/LICENSE
dash_arcgis-0.0.1.dist-info/METADATA
dash_arcgis-0.0.1.dist-info/WHEEL
dash_arcgis-0.0.1.dist-info/top_level.txt
dash_arcgis-0.0.1.dist-info/RECORD
