Metadata-Version: 2.1
Name: dash-arcgis
Version: 0.0.1
Summary: A Public stub for dash-arcgis by Plotly
Home-page: https://plotly.com/dash/
Author: Alex Johnson
Author-email: alex@plotly.com
License: Commercial
Platform: UNKNOWN
Classifier: Programming Language :: Python :: 3
Classifier: Framework :: Dash
